addicty/__init__.py
addicty/_version.py
addicty/addict.py
addicty/s3.py
addicty/yaml_checker.py
addicty-2023.9.3.dist-info/LICENSE
addicty-2023.9.3.dist-info/METADATA
addicty-2023.9.3.dist-info/WHEEL
addicty-2023.9.3.dist-info/top_level.txt
addicty-2023.9.3.dist-info/zip-safe
addicty-2023.9.3.dist-info/RECORD
