Metadata-Version: 2.1
Name: addicty
Version: 2023.9.3
Summary: Addicty is a dictionary whose items can be set using both attribute and item syntax
Home-page: https://github.com/jpn--/addicty
License: MIT
Requires-Python: >=3.7
License-File: LICENSE
Requires-Dist: pyyaml
Requires-Dist: yamllint
